LICENSE.md
MANIFEST.in
README.md
pyproject.toml
setup.cfg
setup.py
versioneer.py
gym_robotics/__init__.py
gym_robotics/_version.py
gym_robotics/core.py
gym_robotics.egg-info/PKG-INFO
gym_robotics.egg-info/SOURCES.txt
gym_robotics.egg-info/dependency_links.txt
gym_robotics.egg-info/entry_points.txt
gym_robotics.egg-info/not-zip-safe
gym_robotics.egg-info/requires.txt
gym_robotics.egg-info/top_level.txt
gym_robotics/envs/__init__.py
gym_robotics/envs/fetch_env.py
gym_robotics/envs/hand_env.py
gym_robotics/envs/robot_env.py
gym_robotics/envs/assets/LICENSE.md
gym_robotics/envs/assets/fetch/pick_and_place.xml
gym_robotics/envs/assets/fetch/push.xml
gym_robotics/envs/assets/fetch/reach.xml
gym_robotics/envs/assets/fetch/robot.xml
gym_robotics/envs/assets/fetch/shared.xml
gym_robotics/envs/assets/fetch/slide.xml
gym_robotics/envs/assets/hand/manipulate_block.xml
gym_robotics/envs/assets/hand/manipulate_block_touch_sensors.xml
gym_robotics/envs/assets/hand/manipulate_egg.xml
gym_robotics/envs/assets/hand/manipulate_egg_touch_sensors.xml
gym_robotics/envs/assets/hand/manipulate_pen.xml
gym_robotics/envs/assets/hand/manipulate_pen_touch_sensors.xml
gym_robotics/envs/assets/hand/reach.xml
gym_robotics/envs/assets/hand/robot.xml
gym_robotics/envs/assets/hand/robot_touch_sensors_92.xml
gym_robotics/envs/assets/hand/shared.xml
gym_robotics/envs/assets/hand/shared_asset.xml
gym_robotics/envs/assets/hand/shared_touch_sensors_92.xml
gym_robotics/envs/assets/stls/fetch/base_link_collision.stl
gym_robotics/envs/assets/stls/fetch/bellows_link_collision.stl
gym_robotics/envs/assets/stls/fetch/elbow_flex_link_collision.stl
gym_robotics/envs/assets/stls/fetch/estop_link.stl
gym_robotics/envs/assets/stls/fetch/forearm_roll_link_collision.stl
gym_robotics/envs/assets/stls/fetch/gripper_link.stl
gym_robotics/envs/assets/stls/fetch/head_pan_link_collision.stl
gym_robotics/envs/assets/stls/fetch/head_tilt_link_collision.stl
gym_robotics/envs/assets/stls/fetch/l_wheel_link_collision.stl
gym_robotics/envs/assets/stls/fetch/laser_link.stl
gym_robotics/envs/assets/stls/fetch/r_wheel_link_collision.stl
gym_robotics/envs/assets/stls/fetch/shoulder_lift_link_collision.stl
gym_robotics/envs/assets/stls/fetch/shoulder_pan_link_collision.stl
