Metadata-Version: 2.1
Name: gym-robotics
Version: 1.0.0
Summary: Legacy robotics environments from Gym repo
Home-page: https://github.com/Farama-Foundation/gym-robotics
Author: Farama Foundation
Author-email: jkterry@farama.org
License: UNKNOWN
Platform: UNKNOWN
Classifier: Programming Language :: Python :: 3
Classifier: Programming Language :: Python :: 3.7
Classifier: Programming Language :: Python :: 3.8
Classifier: Programming Language :: Python :: 3.9
Classifier: Programming Language :: Python :: 3.10
Requires-Python: >=3.7
Provides-Extra: testing
Provides-Extra: mujoco_py
